[
  {
    "word": "xv",
    "paragraphs": [
      "Shaftesbury.MR.2.1.21",
      "Shaftesbury.MR.2.1.32",
      "Shaftesbury.MR.2.1.40",
      "Shaftesbury.MR.5.1.9"
    ]
  },
  {
    "word": "xxiv",
    "paragraphs": [
      "Shaftesbury.JH.3.3"
    ]
  },
  {
    "word": "xii",
    "paragraphs": [
      "Shaftesbury.MR.2.1.34",
      "Shaftesbury.MR.2.2.22",
      "Shaftesbury.MR.2.3.6",
      "Shaftesbury.MR.4.1.6"
    ]
  },
  {
    "word": "xiii",
    "paragraphs": [
      "Shaftesbury.LE.3.2",
      "Shaftesbury.LE.4.1",
      "Shaftesbury.MR.5.1.6",
      "Shaftesbury.MR.5.1.15"
    ]
  },
  {
    "word": "xvii",
    "paragraphs": [
      "Shaftesbury.MR.2.1.36",
      "Shaftesbury.MR.5.1.8"
    ]
  },
  {
    "word": "xviii",
    "paragraphs": [
      "Shaftesbury.LE.6.3",
      "Shaftesbury.LE.6.4",
      "Shaftesbury.MR.2.1.45",
      "Shaftesbury.MR.2.1.47",
      "Shaftesbury.MR.2.3.8",
      "Shaftesbury.MR.2.3.24",
      "Shaftesbury.MR.2.3.29"
    ]
  },
  {
    "word": "xxxvi",
    "paragraphs": [
      "Shaftesbury.MR.2.1.38",
      "Shaftesbury.MR.2.1.41",
      "Shaftesbury.MR.2.1.42"
    ]
  },
  {
    "word": "xxxix",
    "paragraphs": [
      "Shaftesbury.LE.6.8",
      "Shaftesbury.LE.6.9",
      "Shaftesbury.MR.2.1.42"
    ]
  },
  {
    "word": "xx",
    "paragraphs": [
      "Shaftesbury.MR.2.1.40",
      "Shaftesbury.MR.5.1.17"
    ]
  },
  {
    "word": "xi",
    "paragraphs": [
      "Shaftesbury.S.2.2.18",
      "Shaftesbury.MR.2.3.29",
      "Shaftesbury.MR.2.3.29",
      "Shaftesbury.MR.5.1.11",
      "Shaftesbury.MR.5.1.14",
      "Shaftesbury.MR.5.3.5"
    ]
  },
  {
    "word": "xlvii",
    "paragraphs": [
      "Shaftesbury.MR.2.1.43"
    ]
  },
  {
    "word": "xxxii",
    "paragraphs": [
      "Shaftesbury.S.3.1.1",
      "Shaftesbury.MR.2.3.7",
      "Shaftesbury.MR.5.1.16"
    ]
  },
  {
    "word": "xli",
    "paragraphs": [
      "Shaftesbury.MR.2.1.44"
    ]
  },
  {
    "word": "xxxv",
    "paragraphs": [
      "Shaftesbury.S.3.3.9"
    ]
  },
  {
    "word": "xxxvii",
    "paragraphs": [
      "Shaftesbury.MR.2.1.46"
    ]
  },
  {
    "word": "xxii",
    "paragraphs": [
      "Shaftesbury.LE.6.3",
      "Shaftesbury.LE.6.4",
      "Shaftesbury.MR.2.3.23",
      "Shaftesbury.MR.2.3.29"
    ]
  },
  {
    "word": "xenophon",
    "paragraphs": [
      "Shaftesbury.S.2.1.18",
      "Shaftesbury.S.3.3.2"
    ]
  },
  {
    "word": "xxxiv",
    "paragraphs": [
      "Shaftesbury.MR.5.1.13"
    ]
  },
  {
    "word": "xxix",
    "paragraphs": [
      "Shaftesbury.MR.4.1.10"
    ]
  },
  {
    "word": "xxvii",
    "paragraphs": [
      "Shaftesbury.MR.2.3.29"
    ]
  },
  {
    "word": "x",
    "paragraphs": [
      "Shaftesbury.MR.2.3.13"
    ]
  },
  {
    "word": "xenocrates",
    "paragraphs": [
      "Shaftesbury.S.2.2.18"
    ]
  },
  {
    "word": "xiv",
    "paragraphs": [
      "Shaftesbury.LE.6.5",
      "Shaftesbury.MR.3.1.15",
      "Shaftesbury.MR.5.1.10",
      "Shaftesbury.MR.5.1.19"
    ]
  },
  {
    "word": "xix",
    "paragraphs": [
      "Shaftesbury.MR.1.3.3",
      "Shaftesbury.MR.2.2.33",
      "Shaftesbury.MR.2.2.35",
      "Shaftesbury.MR.2.2.37",
      "Shaftesbury.MR.2.3.8",
      "Shaftesbury.MR.2.3.13",
      "Shaftesbury.MR.2.3.13"
    ]
  },
  {
    "word": "xvi",
    "paragraphs": [
      "Shaftesbury.S.3.1.3",
      "Shaftesbury.MR.2.1.7",
      "Shaftesbury.MR.2.3.7"
    ]
  }
]
