{
  "id": "Hume.NHR.15",
  "total": 949,
  "words": [
    {
      "word": "the",
      "count": 74
    },
    {
      "word": "of",
      "count": 52
    },
    {
      "word": "and",
      "count": 35
    },
    {
      "word": "a",
      "count": 21
    },
    {
      "word": "is",
      "count": 18
    },
    {
      "word": "to",
      "count": 18
    },
    {
      "word": "in",
      "count": 16
    },
    {
      "word": "as",
      "count": 14
    },
    {
      "word": "most",
      "count": 12
    },
    {
      "word": "are",
      "count": 11
    },
    {
      "word": "be",
      "count": 11
    },
    {
      "word": "that",
      "count": 11
    },
    {
      "word": "so",
      "count": 10
    },
    {
      "word": "not",
      "count": 9
    },
    {
      "word": "which",
      "count": 9
    },
    {
      "word": "it",
      "count": 8
    },
    {
      "word": "or",
      "count": 7
    },
    {
      "word": "they",
      "count": 7
    },
    {
      "word": "but",
      "count": 6
    },
    {
      "word": "by",
      "count": 6
    },
    {
      "word": "from",
      "count": 6
    },
    {
      "word": "nature",
      "count": 6
    },
    {
      "word": "our",
      "count": 6
    },
    {
      "word": "this",
      "count": 6
    },
    {
      "word": "all",
      "count": 5
    },
    {
      "word": "an",
      "count": 5
    },
    {
      "word": "human",
      "count": 5
    },
    {
      "word": "more",
      "count": 5
    },
    {
      "word": "some",
      "count": 5
    },
    {
      "word": "us",
      "count": 5
    },
    {
      "word": "with",
      "count": 5
    },
    {
      "word": "any",
      "count": 4
    },
    {
      "word": "being",
      "count": 4
    },
    {
      "word": "for",
      "count": 4
    },
    {
      "word": "good",
      "count": 4
    },
    {
      "word": "if",
      "count": 4
    },
    {
      "word": "men",
      "count": 4
    },
    {
      "word": "no",
      "count": 4
    },
    {
      "word": "religious",
      "count": 4
    },
    {
      "word": "scarcely",
      "count": 4
    },
    {
      "word": "them",
      "count": 4
    },
    {
      "word": "we",
      "count": 4
    },
    {
      "word": "what",
      "count": 4
    },
    {
      "word": "will",
      "count": 4
    },
    {
      "word": "attended",
      "count": 3
    },
    {
      "word": "even",
      "count": 3
    },
    {
      "word": "every",
      "count": 3
    },
    {
      "word": "general",
      "count": 3
    },
    {
      "word": "have",
      "count": 3
    },
    {
      "word": "him",
      "count": 3
    },
    {
      "word": "how",
      "count": 3
    },
    {
      "word": "idea",
      "count": 3
    },
    {
      "word": "life",
      "count": 3
    },
    {
      "word": "may",
      "count": 3
    },
    {
      "word": "nothing",
      "count": 3
    },
    {
      "word": "on",
      "count": 3
    },
    {
      "word": "one",
      "count": 3
    },
    {
      "word": "possible",
      "count": 3
    },
    {
      "word": "pure",
      "count": 3
    },
    {
      "word": "ravishing",
      "count": 3
    },
    {
      "word": "such",
      "count": 3
    },
    {
      "word": "their",
      "count": 3
    },
    {
      "word": "thing",
      "count": 3
    },
    {
      "word": "universal",
      "count": 3
    },
    {
      "word": "you",
      "count": 3
    },
    {
      "word": "altogether",
      "count": 2
    },
    {
      "word": "at",
      "count": 2
    },
    {
      "word": "author",
      "count": 2
    },
    {
      "word": "been",
      "count": 2
    },
    {
      "word": "creator",
      "count": 2
    },
    {
      "word": "doubt",
      "count": 2
    },
    {
      "word": "entirely",
      "count": 2
    },
    {
      "word": "examine",
      "count": 2
    },
    {
      "word": "far",
      "count": 2
    },
    {
      "word": "few",
      "count": 2
    },
    {
      "word": "found",
      "count": 2
    },
    {
      "word": "great",
      "count": 2
    },
    {
      "word": "greatest",
      "count": 2
    },
    {
      "word": "happiness",
      "count": 2
    },
    {
      "word": "has",
      "count": 2
    },
    {
      "word": "image",
      "count": 2
    },
    {
      "word": "inexplicable",
      "count": 2
    },
    {
      "word": "intelligent",
      "count": 2
    },
    {
      "word": "intention",
      "count": 2
    },
    {
      "word": "its",
      "count": 2
    },
    {
      "word": "kind",
      "count": 2
    },
    {
      "word": "make",
      "count": 2
    },
    {
      "word": "much",
      "count": 2
    },
    {
      "word": "naturally",
      "count": 2
    },
    {
      "word": "only",
      "count": 2
    },
    {
      "word": "principles",
      "count": 2
    },
    {
      "word": "purpose",
      "count": 2
    },
    {
      "word": "reason",
      "count": 2
    },
    {
      "word": "rise",
      "count": 2
    },
    {
      "word": "set",
      "count": 2
    },
    {
      "word": "should",
      "count": 2
    },
    {
      "word": "single",
      "count": 2
    },
    {
      "word": "sublime",
      "count": 2
    },
    {
      "word": "supreme",
      "count": 2
    },
    {
      "word": "systems",
      "count": 2
    },
    {
      "word": "than",
      "count": 2
    },
    {
      "word": "theological",
      "count": 2
    },
    {
      "word": "though",
      "count": 2
    },
    {
      "word": "understanding",
      "count": 2
    },
    {
      "word": "uniform",
      "count": 2
    },
    {
      "word": "virtue",
      "count": 2
    },
    {
      "word": "visible",
      "count": 2
    },
    {
      "word": "when",
      "count": 2
    },
    {
      "word": "where",
      "count": 2
    },
    {
      "word": "whole",
      "count": 2
    },
    {
      "word": "works",
      "count": 2
    },
    {
      "word": "world",
      "count": 2
    },
    {
      "word": "abandoned",
      "count": 1
    },
    {
      "word": "absurd",
      "count": 1
    },
    {
      "word": "absurdities",
      "count": 1
    },
    {
      "word": "absurdity",
      "count": 1
    },
    {
      "word": "according",
      "count": 1
    },
    {
      "word": "accurate",
      "count": 1
    },
    {
      "word": "adopt",
      "count": 1
    },
    {
      "word": "adopted",
      "count": 1
    },
    {
      "word": "advantages",
      "count": 1
    },
    {
      "word": "ænigma",
      "count": 1
    },
    {
      "word": "afforded",
      "count": 1
    },
    {
      "word": "against",
      "count": 1
    },
    {
      "word": "ages",
      "count": 1
    },
    {
      "word": "allied",
      "count": 1
    },
    {
      "word": "always",
      "count": 1
    },
    {
      "word": "analogy",
      "count": 1
    },
    {
      "word": "another",
      "count": 1
    },
    {
      "word": "appear",
      "count": 1
    },
    {
      "word": "appearance",
      "count": 1
    },
    {
      "word": "appears",
      "count": 1
    },
    {
      "word": "ascribe",
      "count": 1
    },
    {
      "word": "asseverations",
      "count": 1
    },
    {
      "word": "assured",
      "count": 1
    },
    {
      "word": "attain",
      "count": 1
    },
    {
      "word": "attendant",
      "count": 1
    },
    {
      "word": "attributed",
      "count": 1
    },
    {
      "word": "barbarous",
      "count": 1
    },
    {
      "word": "base",
      "count": 1
    },
    {
      "word": "bear",
      "count": 1
    },
    {
      "word": "become",
      "count": 1
    },
    {
      "word": "belief",
      "count": 1
    },
    {
      "word": "believe",
      "count": 1
    },
    {
      "word": "below",
      "count": 1
    },
    {
      "word": "borders",
      "count": 1
    },
    {
      "word": "brutes",
      "count": 1
    },
    {
      "word": "calm",
      "count": 1
    },
    {
      "word": "can",
      "count": 1
    },
    {
      "word": "caprice",
      "count": 1
    },
    {
      "word": "cause",
      "count": 1
    },
    {
      "word": "certain",
      "count": 1
    },
    {
      "word": "character",
      "count": 1
    },
    {
      "word": "chimeras",
      "count": 1
    },
    {
      "word": "chimerical",
      "count": 1
    },
    {
      "word": "comfortable",
      "count": 1
    },
    {
      "word": "common",
      "count": 1
    },
    {
      "word": "compensation",
      "count": 1
    },
    {
      "word": "comprehension",
      "count": 1
    },
    {
      "word": "compunction",
      "count": 1
    },
    {
      "word": "conceive",
      "count": 1
    },
    {
      "word": "concerning",
      "count": 1
    },
    {
      "word": "conditions",
      "count": 1
    },
    {
      "word": "confidence",
      "count": 1
    },
    {
      "word": "confirmed",
      "count": 1
    },
    {
      "word": "confounded",
      "count": 1
    },
    {
      "word": "considered",
      "count": 1
    },
    {
      "word": "consistent",
      "count": 1
    },
    {
      "word": "consult",
      "count": 1
    },
    {
      "word": "contagion",
      "count": 1
    },
    {
      "word": "contemplate",
      "count": 1
    },
    {
      "word": "contention",
      "count": 1
    },
    {
      "word": "contrarieties",
      "count": 1
    },
    {
      "word": "conviction",
      "count": 1
    },
    {
      "word": "corrupt",
      "count": 1
    },
    {
      "word": "could",
      "count": 1
    },
    {
      "word": "course",
      "count": 1
    },
    {
      "word": "creation",
      "count": 1
    },
    {
      "word": "cruel",
      "count": 1
    },
    {
      "word": "cultivated",
      "count": 1
    },
    {
      "word": "cup",
      "count": 1
    },
    {
      "word": "deepest",
      "count": 1
    },
    {
      "word": "degraded",
      "count": 1
    },
    {
      "word": "degrees",
      "count": 1
    },
    {
      "word": "deity",
      "count": 1
    },
    {
      "word": "deliberate",
      "count": 1
    },
    {
      "word": "delightful",
      "count": 1
    },
    {
      "word": "design",
      "count": 1
    },
    {
      "word": "desirable",
      "count": 1
    },
    {
      "word": "destitute",
      "count": 1
    },
    {
      "word": "devotion",
      "count": 1
    },
    {
      "word": "did",
      "count": 1
    },
    {
      "word": "dignifies",
      "count": 1
    },
    {
      "word": "dignify",
      "count": 1
    },
    {
      "word": "disadvantages",
      "count": 1
    },
    {
      "word": "disappointments",
      "count": 1
    },
    {
      "word": "discovered",
      "count": 1
    },
    {
      "word": "discovering",
      "count": 1
    },
    {
      "word": "disfigured",
      "count": 1
    },
    {
      "word": "disgust",
      "count": 1
    },
    {
      "word": "divine",
      "count": 1
    },
    {
      "word": "dogmatical",
      "count": 1
    },
    {
      "word": "draughts",
      "count": 1
    },
    {
      "word": "drawn",
      "count": 1
    },
    {
      "word": "dread",
      "count": 1
    },
    {
      "word": "dreamed",
      "count": 1
    },
    {
      "word": "dreams",
      "count": 1
    },
    {
      "word": "durable",
      "count": 1
    },
    {
      "word": "during",
      "count": 1
    },
    {
      "word": "each",
      "count": 1
    },
    {
      "word": "education",
      "count": 1
    },
    {
      "word": "effusions",
      "count": 1
    },
    {
      "word": "embraced",
      "count": 1
    },
    {
      "word": "eminently",
      "count": 1
    },
    {
      "word": "enabled",
      "count": 1
    },
    {
      "word": "enlarge",
      "count": 1
    },
    {
      "word": "enlarged",
      "count": 1
    },
    {
      "word": "equally",
      "count": 1
    },
    {
      "word": "escape",
      "count": 1
    },
    {
      "word": "establish",
      "count": 1
    },
    {
      "word": "evident",
      "count": 1
    },
    {
      "word": "evil",
      "count": 1
    },
    {
      "word": "exceptions",
      "count": 1
    },
    {
      "word": "exhibited",
      "count": 1
    },
    {
      "word": "existence",
      "count": 1
    },
    {
      "word": "expected",
      "count": 1
    },
    {
      "word": "experience",
      "count": 1
    },
    {
      "word": "exquisite",
      "count": 1
    },
    {
      "word": "fact",
      "count": 1
    },
    {
      "word": "familiarized",
      "count": 1
    },
    {
      "word": "fiction",
      "count": 1
    },
    {
      "word": "fictions",
      "count": 1
    },
    {
      "word": "find",
      "count": 1
    },
    {
      "word": "firm",
      "count": 1
    },
    {
      "word": "first",
      "count": 1
    },
    {
      "word": "flattering",
      "count": 1
    },
    {
      "word": "folly",
      "count": 1
    },
    {
      "word": "form",
      "count": 1
    },
    {
      "word": "frailty",
      "count": 1
    },
    {
      "word": "frame",
      "count": 1
    },
    {
      "word": "fury",
      "count": 1
    },
    {
      "word": "futurity",
      "count": 1
    },
    {
      "word": "genuine",
      "count": 1
    },
    {
      "word": "give",
      "count": 1
    },
    {
      "word": "gives",
      "count": 1
    },
    {
      "word": "glaring",
      "count": 1
    },
    {
      "word": "hand",
      "count": 1
    },
    {
      "word": "happily",
      "count": 1
    },
    {
      "word": "he",
      "count": 1
    },
    {
      "word": "hear",
      "count": 1
    },
    {
      "word": "highest",
      "count": 1
    },
    {
      "word": "himself",
      "count": 1
    },
    {
      "word": "his",
      "count": 1
    },
    {
      "word": "hopes",
      "count": 1
    },
    {
      "word": "however",
      "count": 1
    },
    {
      "word": "hypocrisy",
      "count": 1
    },
    {
      "word": "ignorance",
      "count": 1
    },
    {
      "word": "ill",
      "count": 1
    },
    {
      "word": "immorality",
      "count": 1
    },
    {
      "word": "impiety",
      "count": 1
    },
    {
      "word": "impression",
      "count": 1
    },
    {
      "word": "included",
      "count": 1
    },
    {
      "word": "incomprehensible",
      "count": 1
    },
    {
      "word": "infer",
      "count": 1
    },
    {
      "word": "insensibility",
      "count": 1
    },
    {
      "word": "instinct",
      "count": 1
    },
    {
      "word": "intelligence",
      "count": 1
    },
    {
      "word": "intermingled",
      "count": 1
    },
    {
      "word": "into",
      "count": 1
    },
    {
      "word": "invisible",
      "count": 1
    },
    {
      "word": "irresistible",
      "count": 1
    },
    {
      "word": "joy",
      "count": 1
    },
    {
      "word": "judgment",
      "count": 1
    },
    {
      "word": "jupiter",
      "count": 1
    },
    {
      "word": "keep",
      "count": 1
    },
    {
      "word": "knowledge",
      "count": 1
    },
    {
      "word": "lassitude",
      "count": 1
    },
    {
      "word": "law",
      "count": 1
    },
    {
      "word": "lead",
      "count": 1
    },
    {
      "word": "least",
      "count": 1
    },
    {
      "word": "left-handed",
      "count": 1
    },
    {
      "word": "lives",
      "count": 1
    },
    {
      "word": "look",
      "count": 1
    },
    {
      "word": "madness",
      "count": 1
    },
    {
      "word": "maintains",
      "count": 1
    },
    {
      "word": "man",
      "count": 1
    },
    {
      "word": "mankind",
      "count": 1
    },
    {
      "word": "mark",
      "count": 1
    },
    {
      "word": "maxim",
      "count": 1
    },
    {
      "word": "maxims",
      "count": 1
    },
    {
      "word": "mean",
      "count": 1
    },
    {
      "word": "medal",
      "count": 1
    },
    {
      "word": "mediocrity",
      "count": 1
    },
    {
      "word": "melancholy",
      "count": 1
    },
    {
      "word": "men's",
      "count": 1
    },
    {
      "word": "mind",
      "count": 1
    },
    {
      "word": "misery",
      "count": 1
    },
    {
      "word": "mixed",
      "count": 1
    },
    {
      "word": "moderate",
      "count": 1
    },
    {
      "word": "monkies",
      "count": 1
    },
    {
      "word": "morals",
      "count": 1
    },
    {
      "word": "mother",
      "count": 1
    },
    {
      "word": "must",
      "count": 1
    },
    {
      "word": "mystery",
      "count": 1
    },
    {
      "word": "name",
      "count": 1
    },
    {
      "word": "nations",
      "count": 1
    },
    {
      "word": "necessarily",
      "count": 1
    },
    {
      "word": "noble",
      "count": 1
    },
    {
      "word": "obscure",
      "count": 1
    },
    {
      "word": "obvious",
      "count": 1
    },
    {
      "word": "once",
      "count": 1
    },
    {
      "word": "open",
      "count": 1
    },
    {
      "word": "opinion",
      "count": 1
    },
    {
      "word": "oppose",
      "count": 1
    },
    {
      "word": "opposing",
      "count": 1
    },
    {
      "word": "original",
      "count": 1
    },
    {
      "word": "other",
      "count": 1
    },
    {
      "word": "ourselves",
      "count": 1
    },
    {
      "word": "out",
      "count": 1
    },
    {
      "word": "parts",
      "count": 1
    },
    {
      "word": "people",
      "count": 1
    },
    {
      "word": "perhaps",
      "count": 1
    },
    {
      "word": "persuaded",
      "count": 1
    },
    {
      "word": "philosophy",
      "count": 1
    },
    {
      "word": "piece",
      "count": 1
    },
    {
      "word": "plan",
      "count": 1
    },
    {
      "word": "playsome",
      "count": 1
    },
    {
      "word": "pleasures",
      "count": 1
    },
    {
      "word": "poet",
      "count": 1
    },
    {
      "word": "poet's",
      "count": 1
    },
    {
      "word": "popular",
      "count": 1
    },
    {
      "word": "positive",
      "count": 1
    },
    {
      "word": "possession",
      "count": 1
    },
    {
      "word": "power",
      "count": 1
    },
    {
      "word": "practices",
      "count": 1
    },
    {
      "word": "precepts",
      "count": 1
    },
    {
      "word": "prejudices",
      "count": 1
    },
    {
      "word": "presented",
      "count": 1
    },
    {
      "word": "prevail",
      "count": 1
    },
    {
      "word": "prevailed",
      "count": 1
    },
    {
      "word": "prevails",
      "count": 1
    },
    {
      "word": "principle",
      "count": 1
    },
    {
      "word": "privilege",
      "count": 1
    },
    {
      "word": "produce",
      "count": 1
    },
    {
      "word": "proofs",
      "count": 1
    },
    {
      "word": "propensity",
      "count": 1
    },
    {
      "word": "protestations",
      "count": 1
    },
    {
      "word": "proverbial",
      "count": 1
    },
    {
      "word": "quarrelling",
      "count": 1
    },
    {
      "word": "quickly",
      "count": 1
    },
    {
      "word": "rational",
      "count": 1
    },
    {
      "word": "reasonable",
      "count": 1
    },
    {
      "word": "regard",
      "count": 1
    },
    {
      "word": "regions",
      "count": 1
    },
    {
      "word": "reject",
      "count": 1
    },
    {
      "word": "religion",
      "count": 1
    },
    {
      "word": "religions",
      "count": 1
    },
    {
      "word": "removed",
      "count": 1
    },
    {
      "word": "repose",
      "count": 1
    },
    {
      "word": "representations",
      "count": 1
    },
    {
      "word": "result",
      "count": 1
    },
    {
      "word": "reverse",
      "count": 1
    },
    {
      "word": "riddle",
      "count": 1
    },
    {
      "word": "rigorous",
      "count": 1
    },
    {
      "word": "safety",
      "count": 1
    },
    {
      "word": "same",
      "count": 1
    },
    {
      "word": "scrutiny",
      "count": 1
    },
    {
      "word": "secret",
      "count": 1
    },
    {
      "word": "security",
      "count": 1
    },
    {
      "word": "see",
      "count": 1
    },
    {
      "word": "seems",
      "count": 1
    },
    {
      "word": "selected",
      "count": 1
    },
    {
      "word": "sense",
      "count": 1
    },
    {
      "word": "serious",
      "count": 1
    },
    {
      "word": "severest",
      "count": 1
    },
    {
      "word": "shape",
      "count": 1
    },
    {
      "word": "sharper",
      "count": 1
    },
    {
      "word": "sick",
      "count": 1
    },
    {
      "word": "situation",
      "count": 1
    },
    {
      "word": "small",
      "count": 1
    },
    {
      "word": "smallest",
      "count": 1
    },
    {
      "word": "sometimes",
      "count": 1
    },
    {
      "word": "sovereign",
      "count": 1
    },
    {
      "word": "species",
      "count": 1
    },
    {
      "word": "specimen",
      "count": 1
    },
    {
      "word": "sprightly",
      "count": 1
    },
    {
      "word": "stamp",
      "count": 1
    },
    {
      "word": "station",
      "count": 1
    },
    {
      "word": "strongest",
      "count": 1
    },
    {
      "word": "stupidity",
      "count": 1
    },
    {
      "word": "subject",
      "count": 1
    },
    {
      "word": "suggested",
      "count": 1
    },
    {
      "word": "superstition",
      "count": 1
    },
    {
      "word": "surely",
      "count": 1
    },
    {
      "word": "survey",
      "count": 1
    },
    {
      "word": "suspence",
      "count": 1
    },
    {
      "word": "system",
      "count": 1
    },
    {
      "word": "tells",
      "count": 1
    },
    {
      "word": "temperate",
      "count": 1
    },
    {
      "word": "tenets",
      "count": 1
    },
    {
      "word": "terrifying",
      "count": 1
    },
    {
      "word": "terrors",
      "count": 1
    },
    {
      "word": "theism",
      "count": 1
    },
    {
      "word": "themselves",
      "count": 1
    },
    {
      "word": "theory",
      "count": 1
    },
    {
      "word": "these",
      "count": 1
    },
    {
      "word": "think",
      "count": 1
    },
    {
      "word": "throughout",
      "count": 1
    },
    {
      "word": "thus",
      "count": 1
    },
    {
      "word": "too",
      "count": 1
    },
    {
      "word": "truest",
      "count": 1
    },
    {
      "word": "turn",
      "count": 1
    },
    {
      "word": "uncertainty",
      "count": 1
    },
    {
      "word": "undivided",
      "count": 1
    },
    {
      "word": "uninstructed",
      "count": 1
    },
    {
      "word": "universally",
      "count": 1
    },
    {
      "word": "universe",
      "count": 1
    },
    {
      "word": "upheld",
      "count": 1
    },
    {
      "word": "upon",
      "count": 1
    },
    {
      "word": "vanish",
      "count": 1
    },
    {
      "word": "verbal",
      "count": 1
    },
    {
      "word": "vessel",
      "count": 1
    },
    {
      "word": "vessels",
      "count": 1
    },
    {
      "word": "vice",
      "count": 1
    },
    {
      "word": "view",
      "count": 1
    },
    {
      "word": "views",
      "count": 1
    },
    {
      "word": "voluptuous",
      "count": 1
    },
    {
      "word": "way",
      "count": 1
    },
    {
      "word": "while",
      "count": 1
    },
    {
      "word": "whimsies",
      "count": 1
    },
    {
      "word": "who",
      "count": 1
    },
    {
      "word": "wisdom",
      "count": 1
    },
    {
      "word": "wishes",
      "count": 1
    },
    {
      "word": "wit",
      "count": 1
    },
    {
      "word": "work",
      "count": 1
    },
    {
      "word": "workman",
      "count": 1
    },
    {
      "word": "yet",
      "count": 1
    },
    {
      "word": "zeal",
      "count": 1
    }
  ]
}
